taxOrder/__init__.py
taxOrder/cmdline_taxOrder.py
taxOrder/requirements.txt
taxOrder/taxOrder.py
taxOrder-0.2.7.dist-info/LICENSE
taxOrder-0.2.7.dist-info/METADATA
taxOrder-0.2.7.dist-info/WHEEL
taxOrder-0.2.7.dist-info/entry_points.txt
taxOrder-0.2.7.dist-info/top_level.txt
taxOrder-0.2.7.dist-info/RECORD
